pydantic_storage/__init__.py
pydantic_storage/py.typed
pydantic_storage/_services/__init__.py
pydantic_storage/_services/_managers/__init__.py
pydantic_storage/_services/_managers/_file_manager.py
pydantic_storage/_services/_storages/__init__.py
pydantic_storage/_services/_storages/_file_storage.py
pydantic_storage/abstractions/__init__.py
pydantic_storage/abstractions/_managers/__init__.py
pydantic_storage/abstractions/_managers/_base_manager.py
pydantic_storage/abstractions/_storages/__init__.py
pydantic_storage/abstractions/_storages/_base_file_storage.py
pydantic_storage/backends/__init__.py
pydantic_storage/backends/_file_backends/__init__.py
pydantic_storage/backends/_file_backends/_json_file_storage.py
pydantic_storage/exceptions/__init__.py
pydantic_storage/exceptions/_duplicate_entry_error.py
pydantic_storage/exceptions/_file_data_load_error.py
pydantic_storage/models/__init__.py
pydantic_storage/models/_models.py
pydantic_storage/types/__init__.py
pydantic_storage/types/_generic_types.py
pydantic_storage/types/_model_dict_types.py
pydantic_storage-0.1.1.dist-info/METADATA
pydantic_storage-0.1.1.dist-info/WHEEL
pydantic_storage-0.1.1.dist-info/entry_points.txt
pydantic_storage-0.1.1.dist-info/licenses/LICENSE
pydantic_storage-0.1.1.dist-info/RECORD
