Metadata-Version: 2.4
Name: pydantic-storage
Version: 0.1.1
Summary: A lightweight, type-safe storage system for Pydantic models  with support for multiple backends and persistent storage.
Project-URL: Homepage, https://github.com/shaileshpandit141/pydantic-storage
Project-URL: Repository, https://github.com/shaileshpandit141/pydantic-storage
Project-URL: Issues, https://github.com/shaileshpandit141/pydantic-storage/issues
Author-email: shaileshpandit141 <shaileshpandit141@gmail.com>
License: # MIT License
License-File: LICENSE
Keywords: bulk-create,data-management,data-storage,data-validation,datastore,file-storage,json-storage,lightweight-storage,metadata,model-storage,object-storage,partial-update,persistent-storage,pydantic,pydantic-model,python-storage,python3,schema-validation,structured-storage,type-safe,unique-constraint
Classifier: Development Status :: 3 - Alpha
Classifier: Framework :: Pydantic
Classifier: Intended Audience :: Developers
Classifier: Intended Audience :: Information Technology
Classifier: License :: OSI Approved :: MIT License
Classifier: Natural Language :: English
Classifier: Operating System :: OS Independent
Classifier: Programming Language :: Python
Classifier: Programming Language :: Python :: 3.13
Classifier: Topic :: Database
Classifier: Topic :: File Formats :: JSON
Classifier: Topic :: Security :: Cryptography
Classifier: Topic :: Software Development :: Libraries
Classifier: Topic :: Software Development :: Libraries :: Python Modules
Classifier: Topic :: Software Development :: Testing
Classifier: Topic :: Software Development :: Version Control
Classifier: Topic :: Utilities
Classifier: Typing :: Typed
Requires-Python: >=3.13
Requires-Dist: iniconfig>=2.1.0
Requires-Dist: pydantic>=2.11.7
Provides-Extra: dev
Requires-Dist: mypy; extra == 'dev'
Requires-Dist: pytest; extra == 'dev'
Requires-Dist: ruff; extra == 'dev'
